{
  "generator-jhipster": {
    "promptValues": {
      "packageName": "com.openmarket.dashboard",
      "nativeLanguage": "fr"
    },
    "jhipsterVersion": "4.3.0",
    "baseName": "dashboard",
    "packageName": "com.openmarket.dashboard",
    "packageFolder": "com/openmarket/dashboard",
    "serverPort": "8080",
    "authenticationType": "jwt",
    "hibernateCache": "hazelcast",
    "clusteredHttpSession": false,
    "websocket": false,
    "databaseType": "sql",
    "devDatabaseType": "h2Disk",
    "prodDatabaseType": "mysql",
    "searchEngine": "elasticsearch",
    "messageBroker": false,
    "serviceDiscoveryType": "eureka",
    "buildTool": "maven",
    "enableSocialSignIn": false,
    "jwtSecretKey": "ec6d9974dcdb94c714e56c831327dd6183a6d1f2",
    "clientFramework": "angular2",
    "useSass": true,
    "clientPackageManager": "yarn",
    "applicationType": "gateway",
    "testFrameworks": [
      "protractor"
    ],
    "jhiPrefix": "jhi",
    "enableTranslation": true,
    "nativeLanguage": "fr",
    "languages": [
      "fr",
      "en"
    ]
  }
}